{"AuctionItemId": "147487", "AuctionId": "147019", "CurrentHighPreBid": 1750, "CustomStatus": "Sold", "MyPreBid": 0, "IsWatched": false, "SequenceNumber": 421, "LastCustomStatusSetAt": "2017-02-27T15:50:43.1772178Z", "Year": 2000, "Make": "TOYOTA", "Model": "TUNDRA/SR5", "Odometer": 253161, "Units": "Km", "VehicleLocation": "", "Engine": "GAS", "Transmission": "Auto", "Color": "BLACK", "Brand": "ON-NOT BRANDED", "ExternalAuctionItemId": "10500145", "WinningBidAmount": 1800, "WinningBidLocation": "Montreal", "IsBiddable": true, "Status": 4, "Image": "4f8f75d0fca12f28224b702ef664054e.jpg"}