{"AuctionItemId": "155075", "AuctionId": "154959", "CurrentHighPreBid": 225, "CustomStatus": "Sold", "MyPreBid": 0, "IsWatched": false, "SequenceNumber": 376, "LastCustomStatusSetAt": "2017-03-14T15:53:39.8285488Z", "Year": 2002, "Make": "FORD", "Model": "MUSTANG", "Odometer": 236632, "Units": "Km", "VehicleLocation": "Impact Stouffville", "Engine": "GAS", "Transmission": "Std", "Color": "BROWN", "Brand": "ON-NOT BRANDED", "ExternalAuctionItemId": "10484725", "WinningBidAmount": 650, "WinningBidLocation": "Toronto (Oshawa)", "IsBiddable": true, "Status": 4, "Image": "cf81798d6f9802db9c17f85f97185b5e.jpg"}