{"AuctionItemId": "157745", "AuctionId": "155372", "CurrentHighPreBid": 9100, "CustomStatus": "Sold", "MyPreBid": 0, "IsWatched": false, "SequenceNumber": 538, "LastCustomStatusSetAt": "2017-03-15T18:01:42.6530082Z", "Year": 2011, "Make": "BMW", "Model": "X5 XDRIVE35D", "Odometer": 81573, "Units": "Km", "VehicleLocation": "", "Engine": "GAS", "Transmission": "Auto", "Color": "WHITE", "Brand": "AB-SALVAGE", "ExternalAuctionItemId": "10499245", "WinningBidAmount": 14300, "WinningBidLocation": "Vancouver", "IsBiddable": true, "Status": 4, "Image": "f721434f389828fc992ace0797279c42.jpg"}