{"AuctionItemId": "186126", "AuctionId": "186081", "CurrentHighPreBid": 30100, "CustomStatus": "Sold", "MyPreBid": 0, "IsWatched": false, "SequenceNumber": 15, "LastCustomStatusSetAt": "2017-05-18T13:15:41.4452222Z", "Year": 2014, "Make": "TOYOTA", "Model": "TUNDRA CREWMAX PLATINUM", "Odometer": 64857, "Units": "Km", "VehicleLocation": "", "Engine": "GAS", "Transmission": "Auto", "Color": "WHITE", "Brand": "ON-NOT BRANDED", "ExternalAuctionItemId": "10523737", "WinningBidAmount": 37200, "WinningBidLocation": "Montreal", "IsBiddable": true, "Status": 4, "Image": "445ab06a640f0cb4a1697d3254f65fdf.jpg"}