{"AuctionItemId": "192692", "AuctionId": "190468", "CurrentHighPreBid": 0, "CustomStatus": "If Bid", "MyPreBid": 0, "IsWatched": false, "SequenceNumber": 1, "LastCustomStatusSetAt": "2017-06-06T16:03:09.0291927Z", "Year": 2006, "Make": "TOYOTA", "Model": "TUNDRA LIMITED", "Odometer": 276167, "Units": "Km", "VehicleLocation": "", "Engine": "4.7L GAS", "Transmission": "", "Color": "RED", "Brand": "BC-SALVAGE", "ExternalAuctionItemId": "10512719", "WinningBidAmount": 1100, "WinningBidLocation": "OnSite", "IsBiddable": true, "Status": 4, "Image": "9ffc182b85d60f33b4c725f97bc87f6f.jpg"}