{"AuctionItemId": "200418", "AuctionId": "197967", "CurrentHighPreBid": 25100, "CustomStatus": "Sold", "MyPreBid": 0, "IsWatched": false, "SequenceNumber": 140, "LastCustomStatusSetAt": "2017-06-20T14:22:23.051864Z", "Year": 2016, "Make": "CHEVROLET", "Model": "CAMARO SS", "Odometer": 10923, "Units": "Km", "VehicleLocation": "", "Engine": "GAS", "Transmission": "Auto", "Color": "BLACK", "Brand": "ON-NOT BRANDED", "ExternalAuctionItemId": "10538483", "WinningBidAmount": 35800, "WinningBidLocation": "Montreal", "IsBiddable": true, "Status": 4, "Image": "73931c791e305e69256c08d80146cfd5.jpg"}