{"AuctionItemId": "211333", "AuctionId": "208836", "CurrentHighPreBid": 550, "CustomStatus": "If Bid", "MyPreBid": 0, "IsWatched": false, "SequenceNumber": 687, "LastCustomStatusSetAt": "2017-07-18T18:47:40.8256851Z", "Year": 2001, "Make": "BMW", "Model": "X5 3.0I", "Odometer": 292232, "Units": "Km", "VehicleLocation": "", "Engine": "GAS", "Transmission": "Auto", "Color": "BLACK", "Brand": "ON-NOT BRANDED", "ExternalAuctionItemId": "10568911", "WinningBidAmount": 650, "WinningBidLocation": "Toronto (Oshawa)", "IsBiddable": true, "Status": 4, "Image": "6821db3438235152cec4b9ec11999788.jpg"}