{"AuctionItemId": "215189", "AuctionId": "214871", "CurrentHighPreBid": 16200, "CustomStatus": "Sold", "MyPreBid": 0, "IsWatched": false, "SequenceNumber": 465, "LastCustomStatusSetAt": "2017-07-31T15:15:13.2938199Z", "Year": 2016, "Make": "FORD", "Model": "MUSTANG GT", "Odometer": 12459, "Units": "Km", "VehicleLocation": "", "Engine": "GAS", "Transmission": "Std", "Color": "BLUE", "Brand": "ON-SALVAGE", "ExternalAuctionItemId": "10548076", "WinningBidAmount": 18100, "WinningBidLocation": "Montreal", "IsBiddable": true, "Status": 4, "Image": "6e4d7cc32379208eb0d1401c5ca64864.jpg"}