{"AuctionItemId": "215352", "AuctionId": "215260", "CurrentHighPreBid": 15200, "CustomStatus": "If Bid", "MyPreBid": 0, "IsWatched": false, "SequenceNumber": 364, "LastCustomStatusSetAt": "2017-08-01T15:52:17.1116089Z", "Year": 2016, "Make": "BMW", "Model": "X5", "Odometer": 48465, "Units": "Km", "VehicleLocation": "Impact Stouffville", "Engine": "GAS", "Transmission": "Auto", "Color": "WHITE", "Brand": "ON-SALVAGE", "ExternalAuctionItemId": "10571802", "WinningBidAmount": 23100, "WinningBidLocation": "Toronto (Oshawa)", "IsBiddable": true, "Status": 4, "Image": "34f08b9ff6a2fe07151c9408ca50c645.jpg"}