{"AuctionItemId": "221011", "AuctionId": "220806", "CurrentHighPreBid": 0, "CustomStatus": "Sold", "MyPreBid": 0, "IsWatched": false, "SequenceNumber": 498, "LastCustomStatusSetAt": "2017-08-15T16:53:00.5455234Z", "Year": 2004, "Make": "BMW", "Model": "X5 4.4I", "Odometer": 232716, "Units": "Km", "VehicleLocation": "", "Engine": "GAS", "Transmission": "Auto", "Color": "BLACK", "Brand": "ON-IRREPARABLE", "ExternalAuctionItemId": "10571754", "WinningBidAmount": 275, "WinningBidLocation": "OnSite", "IsBiddable": true, "Status": 4, "Image": "60cf870b18896f000b294464e31c9ade.jpg"}