{"AuctionItemId": "241337", "AuctionId": "241314", "CurrentHighPreBid": 5400, "CustomStatus": "If Bid", "MyPreBid": 0, "IsWatched": false, "SequenceNumber": 401, "LastCustomStatusSetAt": "2017-10-06T14:17:47.8672092Z", "Year": 2015, "Make": "FORD", "Model": "MUSTANG GT", "Odometer": 0, "Units": "Km", "VehicleLocation": "", "Engine": "GAS", "Transmission": "Std", "Color": "BLACK", "Brand": "NO OWNERSHIP", "ExternalAuctionItemId": "10605329", "WinningBidAmount": 6500, "WinningBidLocation": "Toronto (Oshawa)", "IsBiddable": true, "Status": 4, "Image": "f8316feda7e1834fccb9d526260336af.jpg"}