{"AuctionItemId": "245063", "AuctionId": "243684", "CurrentHighPreBid": 0, "CustomStatus": "Sold", "MyPreBid": 0, "IsWatched": false, "SequenceNumber": 440, "LastCustomStatusSetAt": "2017-10-11T14:21:40.7731053Z", "Year": 2003, "Make": "BMW", "Model": "X5 4.4I", "Odometer": 190000, "Units": "Km", "VehicleLocation": "", "Engine": "GAS", "Transmission": "Auto", "Color": "BLACK", "Brand": "NS-SALVAGE", "ExternalAuctionItemId": "10594998", "WinningBidAmount": 575, "WinningBidLocation": "Moncton", "IsBiddable": true, "Status": 4, "Image": "8bfb3f4a09445e9a76267c9040c15ad2.jpg"}