{"AuctionItemId": "284061", "AuctionId": "283943", "CurrentHighPreBid": 3400, "CustomStatus": "Sold", "MyPreBid": 0, "IsWatched": false, "SequenceNumber": 402, "LastCustomStatusSetAt": "2018-01-18T15:40:54.3677685Z", "Year": 2008, "Make": "TOYOTA", "Model": "TUNDRA DOUBLE CAB/DOUBLE CAB SR5", "Odometer": 251030, "Units": "Km", "VehicleLocation": "", "Engine": "GAS", "Transmission": "Auto", "Color": "GREEN", "Brand": "ON-SALVAGE", "ExternalAuctionItemId": "10661812", "WinningBidAmount": 4600, "WinningBidLocation": "Hamilton", "IsBiddable": true, "Status": 4, "Image": "42bfb06c5457900c28eb44fe959c9cce.jpg"}