{"AuctionItemId": "326222", "AuctionId": "323320", "CurrentHighPreBid": 16800, "CustomStatus": "Sold", "MyPreBid": 0, "IsWatched": false, "SequenceNumber": 791, "LastCustomStatusSetAt": "2018-04-10T19:03:33.7287332Z", "Year": 2017, "Make": "TOYOTA", "Model": "TUNDRA DOUBLE CAB SR/SR5/TRD PRO", "Odometer": 37952, "Units": "Km", "VehicleLocation": "", "Engine": "GAS", "Transmission": "Auto", "Color": "WHITE", "Brand": "ON-SALVAGE", "ExternalAuctionItemId": "10702709", "WinningBidAmount": 17700, "WinningBidLocation": "Toronto (Oshawa)", "IsBiddable": true, "Status": 4, "Image": "ac2f95189e97b294c2f3339748f28215.jpg"}