{"AuctionItemId": "337078", "AuctionId": "335125", "CurrentHighPreBid": 175, "CustomStatus": "Sold", "MyPreBid": 0, "IsWatched": false, "SequenceNumber": 560, "LastCustomStatusSetAt": "2018-04-30T16:21:59.024916Z", "Year": 2004, "Make": "FORD", "Model": "MUSTANG", "Odometer": 254927, "Units": "Km", "VehicleLocation": "", "Engine": "GAS", "Transmission": "Auto", "Color": "RED", "Brand": "ON-NOT BRANDED", "ExternalAuctionItemId": "10571451", "WinningBidAmount": 750, "WinningBidLocation": "Toronto (Oshawa)", "IsBiddable": true, "Status": 4, "Image": "5c14cf57ce2aca4ccc17f496304d9c49.jpg"}