{"AuctionItemId": "344952", "AuctionId": "342989", "CurrentHighPreBid": 1300, "CustomStatus": "Sold", "MyPreBid": 0, "IsWatched": false, "SequenceNumber": 544, "LastCustomStatusSetAt": "2018-05-16T17:24:14.4074216Z", "Year": 2006, "Make": "TOYOTA", "Model": "TUNDRA", "Odometer": 228275, "Units": "Km", "VehicleLocation": "", "Engine": "GAS", "Transmission": "Auto", "Color": "GRAY", "Brand": "AB-NON-REPAIRABLE", "ExternalAuctionItemId": "10716805", "WinningBidAmount": 3100, "WinningBidLocation": "Toronto (Oshawa)", "IsBiddable": true, "Status": 4, "Image": "675125cb89dec4b86705f138684653e3.jpg"}